LICENSE
README.md
setup.py
netlink/__init__.py
netlink/attributes.py
netlink/generic.py
netlink/nl80211.py
netlink/route.py
netlink/streams.py
python_netlink.egg-info/PKG-INFO
python_netlink.egg-info/SOURCES.txt
python_netlink.egg-info/dependency_links.txt
python_netlink.egg-info/requires.txt
python_netlink.egg-info/top_level.txt