Metadata-Version: 2.1
Name: python-netlink
Version: 0.0.9
Summary: Asynchronous netlink library for Python
Home-page: https://github.com/kinnay/netlink
Author: Yannik Marchand
Author-email: ymarchand@me.com
License: GPLv3
Platform: Linux
License-File: LICENSE
